SCDF/UnitTests.py
SCDF/__init__.py
SCDF/streamlit_controllerDF.py
streamlit_controllerDF/UnitTests.py
streamlit_controllerDF/__init__.py
streamlit_controllerDF/streamlit_controllerDF.py
streamlit_controllerDF-0.1.3.dist-info/METADATA
streamlit_controllerDF-0.1.3.dist-info/WHEEL
streamlit_controllerDF-0.1.3.dist-info/top_level.txt
streamlit_controllerDF-0.1.3.dist-info/RECORD
