Metadata-Version: 2.1
Name: streamlit-controllerDF
Version: 0.1.3
Summary: A solid base for controlling your data frame, getting quick metrics, and data visualizations using streamlit, pandas, numpy and matplotlib.
Home-page: https://github.com/joshjetson/SCDF/
Author: Joshua Dario
Author-email: joshuajdr@gmail.com
License: MIT
Keywords: Python,streamlit,dataframe,data frame,data set,visualization,automatic,widgets,automation,machine learning,quick,controller,controllerdf,controllerDF,streamlit controller,streamlit data frame,streamlit controllerDF
Classifier: Intended Audience :: Developers
Classifier: License :: OSI Approved :: MIT License
Classifier: Programming Language :: Python
Classifier: Programming Language :: Python :: 3
Classifier: Programming Language :: Python :: 3.6
Classifier: Programming Language :: Python :: 3.7
Classifier: Programming Language :: Python :: 3.8
Classifier: Programming Language :: Python :: 3.9
Classifier: Programming Language :: Python :: 3.10
Classifier: Programming Language :: Python :: 3.11
Classifier: Operating System :: OS Independent
Requires-Dist: streamlit
Requires-Dist: pandas
Requires-Dist: matplotlib
Requires-Dist: numpy
